<?xml version="1.0" encoding="utf-8"?>
<LanguageData>
  <ProducingHormonalSerum.label>生產荷爾蒙血清</ProducingHormonalSerum.label>
  <ProducingHormonalSerum.labelNoun>生產荷爾蒙血清</ProducingHormonalSerum.labelNoun>
  <ProducingHormonalSerum.description>生產荷爾蒙血清</ProducingHormonalSerum.description>
  <ProducingHormonalSerum.stages.0.label>空</ProducingHormonalSerum.stages.0.label>
  <ProducingHormonalSerum.stages.1.label>生產</ProducingHormonalSerum.stages.1.label>
  <ProducingHormonalSerum.stages.2.label>滿</ProducingHormonalSerum.stages.2.label>
</LanguageData>