<?xml version="1.0" encoding="utf-8"?>
<LanguageData>
  <PartookInIncest_Heartbreaking.stages.0.label>被發現亂倫</PartookInIncest_Heartbreaking.stages.0.label>
  <PartookInIncest_Heartbreaking.stages.0.description>我很抱歉，我不知道自己在做什麼。請原諒我…</PartookInIncest_Heartbreaking.stages.0.description>

  <PartookInIncest_Disapproved.stages.0.label>被發現亂倫</PartookInIncest_Disapproved.stages.0.label>
  <PartookInIncest_Disapproved.stages.0.description>嗯，對不起。這是一次錯誤！</PartookInIncest_Disapproved.stages.0.description>

  <PartookInIncest_Acceptable.stages.0.label>被發現亂倫</PartookInIncest_Acceptable.stages.0.label>
  <PartookInIncest_Acceptable.stages.0.description>沒事…沒事。這沒有什麼不對…對吧？</PartookInIncest_Acceptable.stages.0.description>

  <PartookInIncest_Approved.stages.0.label>享受亂倫</PartookInIncest_Approved.stages.0.label>
  <PartookInIncest_Approved.stages.0.description>他們的表情…讓我心跳加速！</PartookInIncest_Approved.stages.0.description>
</LanguageData>